Workbook

Sheet Inputs
A1: RARE EARTHS & CRITICAL MINERALS — COMPARABLE COMPANY ANALYSIS
A2: MP Materials (NYSE: MP) • Lynas Rare Earths (ASX: LYC) • Energy Fuels (NYSE: UUUU) • USA Rare Earth (Nasdaq: USAR) • China Northern Rare Earth (SHA: 600111) • Albemarle (NYSE: ALB)
A3: As of May 2026 | All figures in USD Millions except ratios and capacity (MT/yr)
A5: RAW INPUTS — cell comments cite source / assumption
A6: Company | B6: Ticker | C6: Mkt Cap | D6: Net Debt | E6: Revenue (TTM) | F6: Rev Growth % | G6: Gross Profit | H6: EBITDA (TTM) | I6: Net Income (TTM) | J6: NdPr Cap (MT/yr) | K6: Notes
A7: MP Materials | B7: NYSE: MP | C7: 9810 | D7: 200 | E7: 275 | F7: 0.49 | G7: 83 | H7: -53 | I7: -86 | J7: 6000 | K7: Contains [E] estimates — see cell comments
A8: Lynas Rare Earths | B8: ASX: LYC | C8: 10800 | D8: 0 | E8: 578 | F8: 1.15 | G8: 289 | H8: 211 | I8: 80 | J8: 8800 | K8: Contains [E] estimates — see cell comments
A9: Energy Fuels | B9: NYSE: UUUU | C9: 1500 | D9: -50 | E9: 70 | F9: N/A | G9: N/A | H9: -30 | I9: -50 | J9: 6000 | K9: Contains [E] estimates — see cell comments
A10: USA Rare Earth | B10: Nasdaq: USAR | C10: 1000 | D10: -1500 | E10: 5 | F10: N/A | G10: N/A | H10: -20 | I10: -30 | J10: 1200 | K10: Contains [E] estimates — see cell comments
A11: China Northern Rare Earth | B11: SHA: 600111 | C11: 11500 | D11: 1000 | E11: 5910 | F11: 0.29 | G11: 1182 | H11: 700 | I11: 313 | J11: 60000 | K11: Contains [E] estimates — see cell comments
A12: Albemarle | B12: NYSE: ALB | C12: 22700 | D12: 2300 | E12: 5850 | F12: 0.33 | G12: 1463 | H12: 2500 | I12: 200 | J12: 0 | K12: Contains [E] estimates — see cell comments

Sheet Operating Metrics
A1: OPERATING STATISTICS & FINANCIAL METRICS
A2: All figures USD Millions except margins/growth. Formulas reference Inputs tab.
A4: Company | B4: Revenue (TTM) | C4: Rev Growth (YoY) | D4: Gross Profit | E4: Gross Margin | F4: EBITDA (TTM) | G4: EBITDA Margin
A5: MP Materials | B5: =Inputs!E7 | C5: =IFERROR(Inputs!F7,"N/A") | D5: =IFERROR(Inputs!G7,"N/A") | E5: =IFERROR(Inputs!G7/Inputs!E7,"N/A") | F5: =Inputs!H7 | G5: =IFERROR(Inputs!H7/Inputs!E7,"N/A")
A6: Lynas Rare Earths | B6: =Inputs!E8 | C6: =IFERROR(Inputs!F8,"N/A") | D6: =IFERROR(Inputs!G8,"N/A") | E6: =IFERROR(Inputs!G8/Inputs!E8,"N/A") | F6: =Inputs!H8 | G6: =IFERROR(Inputs!H8/Inputs!E8,"N/A")
A7: Energy Fuels | B7: =Inputs!E9 | C7: =IFERROR(Inputs!F9,"N/A") | D7: =IFERROR(Inputs!G9,"N/A") | E7: =IFERROR(Inputs!G9/Inputs!E9,"N/A") | F7: =Inputs!H9 | G7: =IFERROR(Inputs!H9/Inputs!E9,"N/A")
A8: USA Rare Earth | B8: =Inputs!E10 | C8: =IFERROR(Inputs!F10,"N/A") | D8: =IFERROR(Inputs!G10,"N/A") | E8: =IFERROR(Inputs!G10/Inputs!E10,"N/A") | F8: =Inputs!H10 | G8: =IFERROR(Inputs!H10/Inputs!E10,"N/A")
A9: China Northern Rare Earth | B9: =Inputs!E11 | C9: =IFERROR(Inputs!F11,"N/A") | D9: =IFERROR(Inputs!G11,"N/A") | E9: =IFERROR(Inputs!G11/Inputs!E11,"N/A") | F9: =Inputs!H11 | G9: =IFERROR(Inputs!H11/Inputs!E11,"N/A")
A10: Albemarle | B10: =Inputs!E12 | C10: =IFERROR(Inputs!F12,"N/A") | D10: =IFERROR(Inputs!G12,"N/A") | E10: =IFERROR(Inputs!G12/Inputs!E12,"N/A") | F10: =Inputs!H12 | G10: =IFERROR(Inputs!H12/Inputs!E12,"N/A")
A12: Maximum | C12: =MAX(C5:C10) | E12: =MAX(E5:E10) | G12: =MAX(G5:G10)
A13: 75th Percentile | C13: =QUARTILE(C5:C10,3) | E13: =QUARTILE(E5:E10,3) | G13: =QUARTILE(G5:G10,3)
A14: Median | C14: =MEDIAN(C5:C10) | E14: =MEDIAN(E5:E10) | G14: =MEDIAN(G5:G10)
A15: 25th Percentile | C15: =QUARTILE(C5:C10,1) | E15: =QUARTILE(E5:E10,1) | G15: =QUARTILE(G5:G10,1)
A16: Minimum | C16: =MIN(C5:C10) | E16: =MIN(E5:E10) | G16: =MIN(G5:G10)

Sheet Valuation
A1: VALUATION MULTIPLES
A2: EV = Mkt Cap + Net Debt. NM ("not meaningful") shown for negative denominators.
A4: Company | B4: Mkt Cap | C4: EV | D4: EV / Rev | E4: EV / EBITDA | F4: P / E (TTM) | G4: Comment
A5: MP Materials | B5: =Inputs!C7 | C5: =Inputs!C7+Inputs!D7 | D5: =IFERROR((Inputs!C7+Inputs!D7)/Inputs!E7,"NM") | E5: =IF(Inputs!H7>0,(Inputs!C7+Inputs!D7)/Inputs!H7,"NM") | F5: =IF(Inputs!I7>0,Inputs!C7/Inputs!I7,"NM") | G5: Negative TTM EBITDA → NM; richly priced on revenue; Q1'26 Adj EBITDA inflecting +
A6: Lynas Rare Earths | B6: =Inputs!C8 | C6: =Inputs!C8+Inputs!D8 | D6: =IFERROR((Inputs!C8+Inputs!D8)/Inputs!E8,"NM") | E6: =IF(Inputs!H8>0,(Inputs!C8+Inputs!D8)/Inputs!H8,"NM") | F6: =IF(Inputs!I8>0,Inputs!C8/Inputs!I8,"NM") | G6: Most expensive Western on EV/EBITDA; cheaper than MP on EV/Rev
A7: Energy Fuels | B7: =Inputs!C9 | C7: =Inputs!C9+Inputs!D9 | D7: =IFERROR((Inputs!C9+Inputs!D9)/Inputs!E9,"NM") | E7: =IF(Inputs!H9>0,(Inputs!C9+Inputs!D9)/Inputs!H9,"NM") | F7: =IF(Inputs!I9>0,Inputs!C9/Inputs!I9,"NM") | G7: Pre-meaningful-scale; valuation lens is capacity (see REE-Specific tab)
A8: USA Rare Earth | B8: =Inputs!C10 | C8: =Inputs!C10+Inputs!D10 | D8: =IFERROR((Inputs!C10+Inputs!D10)/Inputs!E10,"NM") | E8: =IF(Inputs!H10>0,(Inputs!C10+Inputs!D10)/Inputs!H10,"NM") | F8: =IF(Inputs!I10>0,Inputs!C10/Inputs!I10,"NM") | G8: Pre-rev magnet pure-play; valuation = optionality on US magnet supply
A9: China Northern Rare Earth | B9: =Inputs!C11 | C9: =Inputs!C11+Inputs!D11 | D9: =IFERROR((Inputs!C11+Inputs!D11)/Inputs!E11,"NM") | E9: =IF(Inputs!H11>0,(Inputs!C11+Inputs!D11)/Inputs!H11,"NM") | F9: =IF(Inputs!I11>0,Inputs!C11/Inputs!I11,"NM") | G9: Cheapest on EV/Rev; un-investable for many Western mandates due to geopolitical risk
A10: Albemarle | B10: =Inputs!C12 | C10: =Inputs!C12+Inputs!D12 | D10: =IFERROR((Inputs!C12+Inputs!D12)/Inputs!E12,"NM") | E10: =IF(Inputs!H12>0,(Inputs!C12+Inputs!D12)/Inputs!H12,"NM") | F10: =IF(Inputs!I12>0,Inputs!C12/Inputs!I12,"NM") | G10: Adjacent commodity (lithium, not REE); included as critical-minerals context
A12: Maximum | D12: =MAX(D5:D10) | E12: =MAX(E5:E10) | F12: =MAX(F5:F10)
A13: 75th Percentile | D13: =QUARTILE(D5:D10,3) | E13: =QUARTILE(E5:E10,3) | F13: =QUARTILE(F5:F10,3)
A14: Median | D14: =MEDIAN(D5:D10) | E14: =MEDIAN(E5:E10) | F14: =MEDIAN(F5:F10)
A15: 25th Percentile | D15: =QUARTILE(D5:D10,1) | E15: =QUARTILE(E5:E10,1) | F15: =QUARTILE(F5:F10,1)
A16: Minimum | D16: =MIN(D5:D10) | E16: =MIN(E5:E10) | F16: =MIN(F5:F10)

Sheet REE-Specific
A1: RARE-EARTH-SPECIFIC METRICS — Capacity-Based Valuation
A2: When EBITDA is negative or scaling, capacity multiples are the cleaner comparable.
A4: Company | B4: EV ($M) | C4: NdPr Capacity (MT/yr) | D4: EV per MT/yr ($M) | E4: Stage Reached | F4: Comment
A5: MP Materials | B5: =Inputs!C7+Inputs!D7 | C5: =Inputs!J7 | D5: =IFERROR((Inputs!C7+Inputs!D7)/Inputs!J7,"N/A") | E5: Mine → Sep + Stage III magnet under build (2028) | F5: Highest $/capacity in Western set — reflects DoD floor + magnet optionality embedded
A6: Lynas Rare Earths | B6: =Inputs!C8+Inputs!D8 | C6: =Inputs!J8 | D6: =IFERROR((Inputs!C8+Inputs!D8)/Inputs!J8,"N/A") | E6: Mine → Sep + Heavy REE (US Seadrift, 2026) | F6: Cheaper on capacity than MP; biggest non-China NdPr volume
A7: Energy Fuels | B7: =Inputs!C9+Inputs!D9 | C7: =Inputs!J9 | D7: =IFERROR((Inputs!C9+Inputs!D9)/Inputs!J9,"N/A") | E7: Processing — REE Phase 2 in BFS, FID Q4'26
A8: USA Rare Earth | B8: =Inputs!C10+Inputs!D10 | C8: =Inputs!J10 | D8: =IFERROR((Inputs!C10+Inputs!D10)/Inputs!J10,"N/A") | E8: Magnet only (Stillwater OK, Q2'26 commercial)
A9: China Northern Rare Earth | B9: =Inputs!C11+Inputs!D11 | C9: =Inputs!J11 | D9: =IFERROR((Inputs!C11+Inputs!D11)/Inputs!J11,"N/A") | E9: Mine → Magnet (fully integrated, state-owned) | F9: Lowest $/capacity globally — scale advantage of incumbent
A10: Albemarle | B10: =Inputs!C12+Inputs!D12 | C10: =Inputs!J12 | D10: =IFERROR((Inputs!C12+Inputs!D12)/Inputs!J12,"N/A") | E10: N/A — lithium / bromine producer | F10: N/A — different commodity
A12: Maximum | D12: =MAX(D5:D10)
A13: 75th Percentile | D13: =QUARTILE(D5:D10,3)
A14: Median | D14: =MEDIAN(D5:D10)
A15: 25th Percentile | D15: =QUARTILE(D5:D10,1)
A16: Minimum | D16: =MIN(D5:D10)

Sheet Notes
A1: NOTES, METHODOLOGY & DATA-SOURCE CAVEATS
A3: Data sources
A4: MCP data sources (S&P Kensho / CapIQ, FactSet, Daloopa) WERE NOT USED — the FSI plugin connectors were not configured in this environment.
A5: Primary public sources: SEC EDGAR (10-Q FY2026 Q1 for MP, USAR), MP investor relations, Lynas reporting centre (H1 FY26, Q3 FY26),
A6: StockAnalysis.com & Yahoo Finance for market data, SMM / Discovery Alert for China Northern Rare Earth FY25 results.
A7: Where required figures were not directly disclosed, an [E] estimate is shown with the assumption documented in the cell comment.
A9: Period definitions
A10: Revenue TTM: rolling four quarters where available; for MP, sum of Q2-Q4 2025 + Q1 2026.
A11: For Lynas, US$ TTM derived from StockAnalysis (US$578M).
A12: For Chinese peers, FY2025 reported figures used (calendar year) — CNY converted at 7.2 CNY/USD.
A13: USAR is pre-commercial revenue — figures are placeholder.
A15: Definitions
... A35: Build script: build_comps.py — re-run to refresh after updating INPUTS dict.
