Workbook

Sheet Inputs
A1: BIG-BOX & OMNICHANNEL RETAIL — COMPARABLE COMPANY ANALYSIS
A2: Walmart (NYSE: WMT) • Costco Wholesale (Nasdaq: COST) • Target (NYSE: TGT) • Amazon (Nasdaq: AMZN) • Kroger (NYSE: KR) • BJ's Wholesale (NYSE: BJ)
A3: As of May 2026 | TTM through FY26 Q1 (Apr 2026) where reported | All $ figures in USD millions except ratios and %
A5: RAW INPUTS — cell comments cite source / assumption
A6: Company | B6: Ticker | C6: Mkt Cap | D6: Net Debt | E6: Revenue (TTM) | F6: Rev Growth % | G6: Gross Profit | H6: EBITDA (TTM) | I6: Net Income (TTM) | J6: Comp Sales % | K6: E-com % of Rev | L6: Ad Revenue ($M) | M6: Mbrshp Rev ($M) | N6: Notes
A7: Walmart | B7: NYSE: WMT | C7: 765000 | D7: 45000 | E7: 685000 | F7: 0.06 | G7: 167000 | H7: 45000 | I7: 17000 | J7: 0.045 | K7: 0.18 | L7: 5000 | M7: 3000 | N7: Contains [E] estimates — see cell comments
A8: Costco Wholesale | B8: Nasdaq: COST | C8: 420000 | D8: -3000 | E8: 270000 | F8: 0.08 | G8: 33750 | H8: 13000 | I8: 8000 | J8: 0.062 | K8: 0.075 | L8: 0 | M8: 5000 | N8: Contains [E] estimates — see cell comments
A9: Target | B9: NYSE: TGT | C9: 70000 | D9: 13000 | E9: 107000 | F9: 0.015 | G9: 29960 | H9: 10000 | I9: 4200 | J9: 0.02 | K9: 0.2 | L9: 2000 | M9: 500 | N9: Contains [E] estimates — see cell comments
A10: Amazon | B10: Nasdaq: AMZN | C10: 2200000 | D10: 30000 | E10: 650000 | F10: 0.1 | G10: 305000 | H10: 160000 | I10: 65000 | J10: N/A | K10: 1 | L10: 60000 | M10: 45000 | N10: Contains [E] estimates — see cell comments
A11: Kroger | B11: NYSE: KR | C11: 50000 | D11: 13000 | E11: 148000 | F11: 0.02 | G11: 32560 | H11: 7000 | I11: 2500 | J11: 0.025 | K11: 0.1 | L11: 1500 | M11: 0 | N11: Contains [E] estimates — see cell comments
A12: BJ's Wholesale | B12: NYSE: BJ | C12: 15000 | D12: 500 | E12: 22000 | F12: 0.05 | G12: 3960 | H12: 1100 | I12: 550 | J12: 0.038 | K12: 0.05 | L12: 0 | M12: 470 | N12: Contains [E] estimates — see cell comments

Sheet Operating Metrics
A1: OPERATING STATISTICS & FINANCIAL METRICS
A2: All $ figures USD millions except margins/growth. Formulas reference Inputs tab.
A4: Company | B4: Revenue (TTM) | C4: Rev Growth (YoY) | D4: Gross Profit | E4: Gross Margin | F4: EBITDA (TTM) | G4: EBITDA Margin
A5: Walmart | B5: =Inputs!E7 | C5: =IFERROR(Inputs!F7,"N/A") | D5: =IFERROR(Inputs!G7,"N/A") | E5: =IFERROR(Inputs!G7/Inputs!E7,"N/A") | F5: =Inputs!H7 | G5: =IFERROR(Inputs!H7/Inputs!E7,"N/A")
A6: Costco Wholesale | B6: =Inputs!E8 | C6: =IFERROR(Inputs!F8,"N/A") | D6: =IFERROR(Inputs!G8,"N/A") | E6: =IFERROR(Inputs!G8/Inputs!E8,"N/A") | F6: =Inputs!H8 | G6: =IFERROR(Inputs!H8/Inputs!E8,"N/A")
A7: Target | B7: =Inputs!E9 | C7: =IFERROR(Inputs!F9,"N/A") | D7: =IFERROR(Inputs!G9,"N/A") | E7: =IFERROR(Inputs!G9/Inputs!E9,"N/A") | F7: =Inputs!H9 | G7: =IFERROR(Inputs!H9/Inputs!E9,"N/A")
A8: Amazon | B8: =Inputs!E10 | C8: =IFERROR(Inputs!F10,"N/A") | D8: =IFERROR(Inputs!G10,"N/A") | E8: =IFERROR(Inputs!G10/Inputs!E10,"N/A") | F8: =Inputs!H10 | G8: =IFERROR(Inputs!H10/Inputs!E10,"N/A")
A9: Kroger | B9: =Inputs!E11 | C9: =IFERROR(Inputs!F11,"N/A") | D9: =IFERROR(Inputs!G11,"N/A") | E9: =IFERROR(Inputs!G11/Inputs!E11,"N/A") | F9: =Inputs!H11 | G9: =IFERROR(Inputs!H11/Inputs!E11,"N/A")
A10: BJ's Wholesale | B10: =Inputs!E12 | C10: =IFERROR(Inputs!F12,"N/A") | D10: =IFERROR(Inputs!G12,"N/A") | E10: =IFERROR(Inputs!G12/Inputs!E12,"N/A") | F10: =Inputs!H12 | G10: =IFERROR(Inputs!H12/Inputs!E12,"N/A")
A12: Maximum | C12: =MAX(C5:C10) | E12: =MAX(E5:E10) | G12: =MAX(G5:G10)
A13: 75th Percentile | C13: =QUARTILE(C5:C10,3) | E13: =QUARTILE(E5:E10,3) | G13: =QUARTILE(G5:G10,3)
A14: Median | C14: =MEDIAN(C5:C10) | E14: =MEDIAN(E5:E10) | G14: =MEDIAN(G5:G10)
A15: 25th Percentile | C15: =QUARTILE(C5:C10,1) | E15: =QUARTILE(E5:E10,1) | G15: =QUARTILE(G5:G10,1)
A16: Minimum | C16: =MIN(C5:C10) | E16: =MIN(E5:E10) | G16: =MIN(G5:G10)

Sheet Valuation
A1: VALUATION MULTIPLES
A2: EV = Market Cap + Net Debt (excl. operating leases). NM where denominator <= 0.
A4: Company | B4: Mkt Cap | C4: EV | D4: EV / Rev | E4: EV / EBITDA | F4: P / E (TTM) | G4: Comment
A5: Walmart | B5: =Inputs!C7 | C5: =Inputs!C7+Inputs!D7 | D5: =IFERROR((Inputs!C7+Inputs!D7)/Inputs!E7,"NM") | E5: =IF(Inputs!H7>0,(Inputs!C7+Inputs!D7)/Inputs!H7,"NM") | F5: =IF(Inputs!I7>0,Inputs!C7/Inputs!I7,"NM") | G5: Re-rating in progress as ad/marketplace mix expands EBITDA margin
A6: Costco Wholesale | B6: =Inputs!C8 | C6: =Inputs!C8+Inputs!D8 | D6: =IFERROR((Inputs!C8+Inputs!D8)/Inputs!E8,"NM") | E6: =IF(Inputs!H8>0,(Inputs!C8+Inputs!D8)/Inputs!H8,"NM") | F6: =IF(Inputs!I8>0,Inputs!C8/Inputs!I8,"NM") | G6: Premium-priced peer; membership economics support 40%+ P/E premium to WMT
A7: Target | B7: =Inputs!C9 | C7: =Inputs!C9+Inputs!D9 | D7: =IFERROR((Inputs!C9+Inputs!D9)/Inputs!E9,"NM") | E7: =IF(Inputs!H9>0,(Inputs!C9+Inputs!D9)/Inputs!H9,"NM") | F7: =IF(Inputs!I9>0,Inputs!C9/Inputs!I9,"NM") | G7: Cheapest large-cap mass merchant; pricing-in slower comp recovery
A8: Amazon | B8: =Inputs!C10 | C8: =Inputs!C10+Inputs!D10 | D8: =IFERROR((Inputs!C10+Inputs!D10)/Inputs!E10,"NM") | E8: =IF(Inputs!H10>0,(Inputs!C10+Inputs!D10)/Inputs!H10,"NM") | F8: =IF(Inputs!I10>0,Inputs!C10/Inputs!I10,"NM") | G8: Headline multiples reflect AWS economics; retail-only would screen differently
A9: Kroger | B9: =Inputs!C11 | C9: =Inputs!C11+Inputs!D11 | D9: =IFERROR((Inputs!C11+Inputs!D11)/Inputs!E11,"NM") | E9: =IF(Inputs!H11>0,(Inputs!C11+Inputs!D11)/Inputs!H11,"NM") | F9: =IF(Inputs!I11>0,Inputs!C11/Inputs!I11,"NM") | G9: Pure-play grocery; thin EBITDA margin caps multiple expansion
A10: BJ's Wholesale | B10: =Inputs!C12 | C10: =Inputs!C12+Inputs!D12 | D10: =IFERROR((Inputs!C12+Inputs!D12)/Inputs!E12,"NM") | E10: =IF(Inputs!H12>0,(Inputs!C12+Inputs!D12)/Inputs!H12,"NM") | F10: =IF(Inputs!I12>0,Inputs!C12/Inputs!I12,"NM") | G10: Warehouse-club discount to COST; smaller scale, weaker membership renewal data
A12: Maximum | D12: =MAX(D5:D10) | E12: =MAX(E5:E10) | F12: =MAX(F5:F10)
A13: 75th Percentile | D13: =QUARTILE(D5:D10,3) | E13: =QUARTILE(E5:E10,3) | F13: =QUARTILE(F5:F10,3)
A14: Median | D14: =MEDIAN(D5:D10) | E14: =MEDIAN(E5:E10) | F14: =MEDIAN(F5:F10)
A15: 25th Percentile | D15: =QUARTILE(D5:D10,1) | E15: =QUARTILE(E5:E10,1) | F15: =QUARTILE(F5:F10,1)
A16: Minimum | D16: =MIN(D5:D10) | E16: =MIN(E5:E10) | F16: =MIN(F5:F10)

Sheet Retail-Specific
A1: RETAIL-SPECIFIC METRICS — Comp Sales, Mix, Ads & Membership
A2: Industry-defining metrics: comparable sales, e-com penetration, and the high-margin tiers (ads + membership) that drive margin mix.
A4: Company | B4: Comp Sales % | C4: E-com % of Rev | D4: Ad Revenue ($M) | E4: Ad % of Rev | F4: Membership Rev ($M) | G4: Mbrshp % of Rev | H4: Posture
A5: Walmart | B5: =IFERROR(Inputs!J7,"N/A") | C5: =IFERROR(Inputs!K7,"N/A") | D5: =Inputs!L7 | E5: =IFERROR(Inputs!L7/Inputs!E7,"N/A") | F5: =Inputs!M7 | G5: =IFERROR(Inputs!M7/Inputs!E7,"N/A") | H5: Scale incumbent — building ad + marketplace + Walmart+ on top of grocery flywheel
A6: Costco Wholesale | B6: =IFERROR(Inputs!J8,"N/A") | C6: =IFERROR(Inputs!K8,"N/A") | D6: =Inputs!L8 | E6: =IFERROR(Inputs!L8/Inputs!E8,"N/A") | F6: =Inputs!M8 | G6: =IFERROR(Inputs!M8/Inputs!E8,"N/A") | H6: Membership-first warehouse club — premium loyalty, low-margin merchandise
A7: Target | B7: =IFERROR(Inputs!J9,"N/A") | C7: =IFERROR(Inputs!K9,"N/A") | D7: =Inputs!L9 | E7: =IFERROR(Inputs!L9/Inputs!E9,"N/A") | F7: =Inputs!M9 | G7: =IFERROR(Inputs!M9/Inputs!E9,"N/A") | H7: Cheap-chic mass — Roundel ad business is the bright spot in a soft topline
A8: Amazon | B8: =IFERROR(Inputs!J10,"N/A") | C8: =IFERROR(Inputs!K10,"N/A") | D8: =Inputs!L10 | E8: =IFERROR(Inputs!L10/Inputs!E10,"N/A") | F8: =Inputs!M10 | G8: =IFERROR(Inputs!M10/Inputs!E10,"N/A") | H8: Marketplace-first — ad business is ~10% of revenue and the highest-margin retail tier
A9: Kroger | B9: =IFERROR(Inputs!J11,"N/A") | C9: =IFERROR(Inputs!K11,"N/A") | D9: =Inputs!L11 | E9: =IFERROR(Inputs!L11/Inputs!E11,"N/A") | F9: =Inputs!M11 | G9: =IFERROR(Inputs!M11/Inputs!E11,"N/A") | H9: Pure-play grocer — Precision Marketing ad business is the margin lever
A10: BJ's Wholesale | B10: =IFERROR(Inputs!J12,"N/A") | C10: =IFERROR(Inputs!K12,"N/A") | D10: =Inputs!L12 | E10: =IFERROR(Inputs!L12/Inputs!E12,"N/A") | F10: =Inputs!M12 | G10: =IFERROR(Inputs!M12/Inputs!E12,"N/A") | H10: Sub-scale COST follower — value-led, limited ad/digital optionality
A12: Maximum | B12: =MAX(B5:B10) | C12: =MAX(C5:C10) | E12: =MAX(E5:E10) | G12: =MAX(G5:G10)
A13: 75th Percentile | B13: =QUARTILE(B5:B10,3) | C13: =QUARTILE(C5:C10,3) | E13: =QUARTILE(E5:E10,3) | G13: =QUARTILE(G5:G10,3)
A14: Median | B14: =MEDIAN(B5:B10) | C14: =MEDIAN(C5:C10) | E14: =MEDIAN(E5:E10) | G14: =MEDIAN(G5:G10)
A15: 25th Percentile | B15: =QUARTILE(B5:B10,1) | C15: =QUARTILE(C5:C10,1) | E15: =QUARTILE(E5:E10,1) | G15: =QUARTILE(G5:G10,1)
A16: Minimum | B16: =MIN(B5:B10) | C16: =MIN(C5:C10) | E16: =MIN(E5:E10) | G16: =MIN(G5:G10)

Sheet Notes
A1: NOTES, METHODOLOGY & DATA-SOURCE CAVEATS
A3: Data sources
A4: MCP data sources (S&P Kensho / CapIQ, FactSet, Daloopa) WERE NOT USED — the FSI plugin connectors were not configured in this environment.
A5: Primary public sources: SEC EDGAR (10-K FY25 and 10-Q FY26 Q1 for each issuer), company IR releases, StockAnalysis.com / Yahoo Finance for market data.
A6: Where required figures were not directly disclosed, an [E] estimate is shown with the underlying assumption documented in the cell comment.
A8: Period definitions
A9: WMT, TGT, COST use fiscal years offset from calendar — FY26 Q1 maps to calendar Feb-Apr 2026 (WMT) / Mar-May 2026 (TGT) / Feb-May 2026 (COST).
A10: AMZN, KR, BJ use calendar-year reporting; AMZN Q1 FY26 = Jan-Mar 2026.
A11: TTM = trailing four reported quarters as of latest filing; mixed fiscal-year ends are flagged where material.
A12: Comparable / identical sales: per each issuer's published definition; ex-fuel for WMT/KR/BJ; ex-gasoline/FX for COST; ex-gas for KR.
A14: Definitions
A15: EV = Market Cap + Net Debt (Total Debt - Cash). Operating-lease liabilities excluded — they are material for AMZN especially; flagged in Notes.
... A35: Build script: build_comps.py — re-run to refresh after updating INPUTS dict.
